{"_invocation_id": "fae00c76-8cfa-4f7b-9c33-d9a995384cdf", "linked": {"0": {"name": "source.flights_dbt.raw.airlines", "type": "source"}, "1": {"name": "source.flights_dbt.raw.flights", "type": "source"}, "2": {"name": "source.flights_dbt.raw.airports", "type": "source"}, "3": {"name": "source.flights_dbt.raw_flights.flights", "type": "source", "succ": [14]}, "4": {"name": "source.flights_dbt.raw_flights.airports", "type": "source", "succ": [16]}, "5": {"name": "source.flights_dbt.raw_flights.airlines", "type": "source", "succ": [18]}, "6": {"name": "model.flights_dbt.stg_airlines", "type": "model"}, "7": {"name": "model.flights_dbt.my_first_dbt_model", "type": "model", "succ": [8, 9, 10]}, "8": {"name": "test.flights_dbt.unique_my_first_dbt_model_flight_id.bf2f32ffd8", "type": "test"}, "9": {"name": "test.flights_dbt.not_null_my_first_dbt_model_flight_id.42d41aed00", "type": "test"}, "10": {"name": "model.flights_dbt.my_second_dbt_model", "type": "model", "succ": [11, 12]}, "11": {"name": "test.flights_dbt.unique_my_second_dbt_model_flight_id.80fe921580", "type": "test"}, "12": {"name": "test.flights_dbt.not_null_my_second_dbt_model_flight_id.718e911b9d", "type": "test"}, "13": {"name": "model.flights_dbt.silver_flights", "type": "model", "succ": [19]}, "14": {"name": "model.flights_dbt.bronze_flights", "type": "model", "succ": [13]}, "15": {"name": "model.flights_dbt.silver_airports", "type": "model", "succ": [19]}, "16": {"name": "model.flights_dbt.bronze_airports", "type": "model", "succ": [15]}, "17": {"name": "model.flights_dbt.silver_airlines", "type": "model", "succ": [19]}, "18": {"name": "model.flights_dbt.bronze_airlines", "type": "model", "succ": [17]}, "19": {"name": "model.flights_dbt.gold_flight_metrics", "type": "model"}}, "with_test_edges": {"0": {"name": "source.flights_dbt.raw.airlines", "type": "source"}, "1": {"name": "source.flights_dbt.raw.flights", "type": "source"}, "2": {"name": "source.flights_dbt.raw.airports", "type": "source"}, "3": {"name": "source.flights_dbt.raw_flights.flights", "type": "source", "succ": [14]}, "4": {"name": "source.flights_dbt.raw_flights.airports", "type": "source", "succ": [16]}, "5": {"name": "source.flights_dbt.raw_flights.airlines", "type": "source", "succ": [18]}, "6": {"name": "model.flights_dbt.stg_airlines", "type": "model"}, "7": {"name": "model.flights_dbt.my_first_dbt_model", "type": "model", "succ": [8, 9, 10]}, "8": {"name": "test.flights_dbt.unique_my_first_dbt_model_flight_id.bf2f32ffd8", "type": "test", "succ": [10]}, "9": {"name": "test.flights_dbt.not_null_my_first_dbt_model_flight_id.42d41aed00", "type": "test", "succ": [10]}, "10": {"name": "model.flights_dbt.my_second_dbt_model", "type": "model", "succ": [11, 12]}, "11": {"name": "test.flights_dbt.unique_my_second_dbt_model_flight_id.80fe921580", "type": "test"}, "12": {"name": "test.flights_dbt.not_null_my_second_dbt_model_flight_id.718e911b9d", "type": "test"}, "13": {"name": "model.flights_dbt.silver_flights", "type": "model", "succ": [19]}, "14": {"name": "model.flights_dbt.bronze_flights", "type": "model", "succ": [13]}, "15": {"name": "model.flights_dbt.silver_airports", "type": "model", "succ": [19]}, "16": {"name": "model.flights_dbt.bronze_airports", "type": "model", "succ": [15]}, "17": {"name": "model.flights_dbt.silver_airlines", "type": "model", "succ": [19]}, "18": {"name": "model.flights_dbt.bronze_airlines", "type": "model", "succ": [17]}, "19": {"name": "model.flights_dbt.gold_flight_metrics", "type": "model"}}}